{
  "data": {
    "article": {},
    "attachments": {
      "media_keys": [
        "3_2069934317489594368"
      ]
    },
    "author_id": "2065149033379971072",
    "conversation_id": "2069935153326268497",
    "created_at": "2026-06-25T00:06:12.000Z",
    "edit_controls": {
      "editable_until": "2026-06-25T01:02:54.000Z",
      "edits_remaining": 2,
      "is_edit_eligible": true
    },
    "edit_history_tweet_ids": [
      "2069934320341684611",
      "2069934624873349610",
      "2069934935713145158",
      "2069935153326268497"
    ],
    "entities": {
      "urls": [
        {
          "display_url": "pic.x.com/Uz0gx0YPkq",
          "end": 78,
          "expanded_url": "https://x.com/Lomyral896444/status/2069935153326268497/photo/1",
          "media_key": "3_2069934317489594368",
          "start": 55,
          "url": "https://t.co/Uz0gx0YPkq"
        }
      ]
    },
    "geo": {},
    "id": "2069935153326268497",
    "lang": "zh",
    "note_tweet": {
      "entities": {}
    },
    "possibly_sensitive": false,
    "public_metrics": {
      "bookmark_count": 0,
      "impression_count": 0,
      "like_count": 0,
      "quote_count": 0,
      "reply_count": 0,
      "retweet_count": 0
    },
    "reply_settings": "everyone",
    "text": "小时候看这集话费倒欠一万块，家附近的营业厅第二天就铺上金砖地板了。\n\n顺便是的你怎么知道我们又聊了一个通宵🤓 https://t.co/Uz0gx0YPkq"
  },
  "includes": {
    "media": [
      {
        "height": 419,
        "media_key": "3_2069934317489594368",
        "public_metrics": {},
        "type": "photo",
        "url": "https://pbs.twimg.com/media/HLniS3ZboAAolZ3.jpg",
        "width": 748
      }
    ],
    "tweets": [
      {
        "article": {},
        "attachments": {
          "media_keys": [
            "3_2069934317489594368"
          ]
        },
        "author_id": "2065149033379971072",
        "conversation_id": "2069934320341684611",
        "created_at": "2026-06-25T00:02:54.000Z",
        "edit_controls": {
          "editable_until": "2026-06-25T01:02:54.000Z",
          "edits_remaining": 2,
          "is_edit_eligible": true
        },
        "edit_history_tweet_ids": [
          "2069934320341684611",
          "2069934624873349610",
          "2069934935713145158",
          "2069935153326268497"
        ],
        "entities": {
          "urls": [
            {
              "display_url": "pic.x.com/lH9E7Zgzvt",
              "end": 37,
              "expanded_url": "https://x.com/Lomyral896444/status/2069934320341684611/photo/1",
              "media_key": "3_2069934317489594368",
              "start": 14,
              "url": "https://t.co/lH9E7Zgzvt"
            }
          ]
        },
        "geo": {},
        "id": "2069934320341684611",
        "lang": "zh",
        "note_tweet": {
          "entities": {}
        },
        "possibly_sensitive": false,
        "public_metrics": {
          "bookmark_count": 0,
          "impression_count": 3,
          "like_count": 0,
          "quote_count": 0,
          "reply_count": 0,
          "retweet_count": 0
        },
        "reply_settings": "everyone",
        "text": "小时候看这集欠了一万块话费 https://t.co/lH9E7Zgzvt"
      },
      {
        "article": {},
        "attachments": {
          "media_keys": [
            "3_2069934317489594368"
          ]
        },
        "author_id": "2065149033379971072",
        "conversation_id": "2069934624873349610",
        "created_at": "2026-06-25T00:04:06.000Z",
        "edit_controls": {
          "editable_until": "2026-06-25T01:02:54.000Z",
          "edits_remaining": 2,
          "is_edit_eligible": true
        },
        "edit_history_tweet_ids": [
          "2069934320341684611",
          "2069934624873349610",
          "2069934935713145158",
          "2069935153326268497"
        ],
        "entities": {
          "urls": [
            {
              "display_url": "pic.x.com/7td5MA2GV6",
              "end": 55,
              "expanded_url": "https://x.com/Lomyral896444/status/2069934624873349610/photo/1",
              "media_key": "3_2069934317489594368",
              "start": 32,
              "url": "https://t.co/7td5MA2GV6"
            }
          ]
        },
        "geo": {},
        "id": "2069934624873349610",
        "lang": "zh",
        "note_tweet": {
          "entities": {}
        },
        "possibly_sensitive": false,
        "public_metrics": {
          "bookmark_count": 0,
          "impression_count": 2,
          "like_count": 0,
          "quote_count": 0,
          "reply_count": 0,
          "retweet_count": 0
        },
        "reply_settings": "everyone",
        "text": "小时候看这集欠了一万块话费，家附近营业厅第二天就铺上金砖地板了 https://t.co/7td5MA2GV6"
      },
      {
        "article": {},
        "attachments": {
          "media_keys": [
            "3_2069934317489594368"
          ]
        },
        "author_id": "2065149033379971072",
        "conversation_id": "2069934935713145158",
        "created_at": "2026-06-25T00:05:20.000Z",
        "edit_controls": {
          "editable_until": "2026-06-25T01:02:54.000Z",
          "edits_remaining": 2,
          "is_edit_eligible": true
        },
        "edit_history_tweet_ids": [
          "2069934320341684611",
          "2069934624873349610",
          "2069934935713145158",
          "2069935153326268497"
        ],
        "entities": {
          "urls": [
            {
              "display_url": "pic.x.com/2djDPlHFIq",
              "end": 56,
              "expanded_url": "https://x.com/Lomyral896444/status/2069934935713145158/photo/1",
              "media_key": "3_2069934317489594368",
              "start": 33,
              "url": "https://t.co/2djDPlHFIq"
            }
          ]
        },
        "geo": {},
        "id": "2069934935713145158",
        "lang": "zh",
        "note_tweet": {
          "entities": {}
        },
        "possibly_sensitive": false,
        "public_metrics": {
          "bookmark_count": 0,
          "impression_count": 1,
          "like_count": 0,
          "quote_count": 0,
          "reply_count": 0,
          "retweet_count": 0
        },
        "reply_settings": "everyone",
        "text": "小时候看这集话费盗窃一万块，家附近的营业厅第二天就铺上金砖地板了 https://t.co/2djDPlHFIq"
      },
      {
        "article": {},
        "attachments": {
          "media_keys": [
            "3_2069934317489594368"
          ]
        },
        "author_id": "2065149033379971072",
        "conversation_id": "2069935153326268497",
        "created_at": "2026-06-25T00:06:12.000Z",
        "edit_controls": {
          "editable_until": "2026-06-25T01:02:54.000Z",
          "edits_remaining": 2,
          "is_edit_eligible": true
        },
        "edit_history_tweet_ids": [
          "2069934320341684611",
          "2069934624873349610",
          "2069934935713145158",
          "2069935153326268497"
        ],
        "entities": {
          "urls": [
            {
              "display_url": "pic.x.com/Uz0gx0YPkq",
              "end": 78,
              "expanded_url": "https://x.com/Lomyral896444/status/2069935153326268497/photo/1",
              "media_key": "3_2069934317489594368",
              "start": 55,
              "url": "https://t.co/Uz0gx0YPkq"
            }
          ]
        },
        "geo": {},
        "id": "2069935153326268497",
        "lang": "zh",
        "note_tweet": {
          "entities": {}
        },
        "possibly_sensitive": false,
        "public_metrics": {
          "bookmark_count": 0,
          "impression_count": 0,
          "like_count": 0,
          "quote_count": 0,
          "reply_count": 0,
          "retweet_count": 0
        },
        "reply_settings": "everyone",
        "text": "小时候看这集话费倒欠一万块，家附近的营业厅第二天就铺上金砖地板了。\n\n顺便是的你怎么知道我们又聊了一个通宵🤓 https://t.co/Uz0gx0YPkq"
      }
    ],
    "users": [
      {
        "created_at": "2026-06-11T19:09:32.000Z",
        "description": "enby，he/they|\nINTP/重抑中焦|\n碎碎念推。不鉴证，不吸毒，不贩毒，不提供任何付费服务|\n这里是四号机，互关寻回中|三号机：@Lomyral114514|最爱的骚b❤️：@TheB17w153",
        "entities": {
          "description": {
            "mentions": [
              {
                "end": 84,
                "start": 70,
                "username": "Lomyral114514"
              },
              {
                "end": 104,
                "start": 93,
                "username": "TheB17w153"
              }
            ]
          },
          "url": {
            "urls": [
              {
                "display_url": "ngl.link/lomyral",
                "end": 23,
                "expanded_url": "https://ngl.link/lomyral",
                "start": 0,
                "url": "https://t.co/QwIZQw05Ms"
              }
            ]
          }
        },
        "id": "2065149033379971072",
        "name": "Lomyral 4.0",
        "pinned_tweet_id": "2065235638568493134",
        "profile_image_url": "https://pbs.twimg.com/profile_images/2065150134065954816/FdqO6LUP_normal.jpg",
        "protected": false,
        "public_metrics": {
          "followers_count": 564,
          "following_count": 408,
          "like_count": 2697,
          "listed_count": 0,
          "media_count": 33,
          "tweet_count": 651
        },
        "url": "https://t.co/QwIZQw05Ms",
        "username": "Lomyral896444",
        "verified": true
      }
    ]
  }
}